{
  "articles": [
    {
      "articleId": 20210010,
      "dateOfPublish": "2021-04-16",
      "title": "Klubové zkoušky vloh ohařů",
      "paragraphs": [
        "Také máme v plánu uspořádat klubové zkoušky vloh ohařů, které se uskuteční 16. května v Těšanech. Bude zadáváno čekatelství CACT, RES. CACT.",
        "Věříme, že se zde setkáme v hojném počtu."
      ],
      "images": [
        "./public/pdf/2021/210516-klubove_vlohy/plakat.jpg"
      ],
      "attachments": [
        {
          "description": "pozvánka",
          "filePath": "./public/pdf/2021/210516-klubove_vlohy/plakat.jpg",
          "type": "jpg"
        },
        {
          "description": "propozice",
          "filePath": "./public/pdf/2021/210516-klubove_vlohy/propozice.pdf",
          "type": "pdf"
        },
        {
          "description": "přihláška",
          "filePath": "./public/pdf/2021/210516-klubove_vlohy/prihlaska.docx",
          "type": "doc"
        }
      ]
    },
    {
      "articleId": 20210009,
      "dateOfPublish": "2021-04-16",
      "title": "Klubové podzimní zkoušky ohařů",
      "paragraphs": [
        "Letos se budou konat klubové podzimní zkoušky ohařů 15. května v Těšanech. Bude zadáváno čekatelství CACT, RES. CACT.",
        "Na vaši účast se velice těšíme."
      ],
      "images": [
        "./public/pdf/2021/210515-klubove_podzimni_zkousky/plakat.jpg"
      ],
      "attachments": [
        {
          "description": "pozvánka",
          "filePath": "./public/pdf/2021/210515-klubove_podzimni_zkousky/plakat.jpg",
          "type": "jpg"
        },
        {
          "description": "propozice",
          "filePath": "./public/pdf/2021/210515-klubove_podzimni_zkousky/propozice.pdf",
          "type": "pdf"
        },
        {
          "description": "přihláška",
          "filePath": "./public/pdf/2021/210515-klubove_podzimni_zkousky/prihlaska.docx",
          "type": "doc"
        }
      ]
    },
    {
      "articleId": 20210008,
      "dateOfPublish": "4/8/2021",
      "title": "Klubová výstava ve Slavkově",
      "paragraphs": [
        "Letos opět v netradičním termínu. Věřme ale, že se ve Slavkově potkáme ve zdraví a v dobré náladě."
      ],
      "images": [
        "./public/images/2021/210710-klubovka_slavkov_u_brna.jpg"
      ],
      "attachments": [
        {
          "description": "propozice",
          "filePath": "./public/pdf/2021/210710-klubovka_slavkov/propozice-cz.pdf",
          "type": "pdf"
        },
        {
          "description": "proposition (EN)",
          "filePath": "./public/pdf/2021/210710-klubovka_slavkov/propozice-en.pdf",
          "type": "pdf"
        }
      ]
    },
    {
      "articleId": 9999999999999,
      "dateOfPublish": "4/8/2021",
      "title": "Kalendář klubových akcí",
      "paragraphs": [
        "Vážení návštěvníci,",
        "na našich stránkách najdete aktualizovaný <a href=\"kalendar_akci.html#2021\">kalendář klubových akcí na rok 2021</a>.",
        "Pevně věříme, že se s mnohými z vás na některých z nich potkáme."
      ]
    },
    {
      "articleId": 9999999999999,
      "dateOfPublish": "3/23/2021",
      "title": "Přihlašování na Světovou Výstavu Psů v Brně",
      "paragraphs": [
        "Vážení vystavovatelé,",
        "Po dlouhých a náročných jednáních přicházíme s dobrou zprávou. Sporné momenty spojené s pořádáním Světové Výstavy Psů v Brně jsou projednány a přihlašování na světovou výstavu je znovu otevřeno.",
        "2. uzávěrka je posunuta o 15 dní, po které bylo přihlašování pozastaveno, tj. do 15.4.2021.",
        "Doufejme, že žádné další překážky nebude nutno překonávat a my se všichni v plném zdraví a síle sejdeme na této prestižní kynologické akci.",
        "Lubomír Široký",
        "Předseda ČMKU"
      ],
      "images": [
        "./public/images/2021/2021-cmku_logo.jpg"
      ]
    },
    {
      "articleId": 9999999999999,
      "dateOfPublish": "3/16/2021",
      "title": "Členské příspěvky",
      "paragraphs": [
        "Vážení členové klubu, dovoluji si tímto upozornit na splatnost členských příspěvků na rok 2021.",
        "Vzhledem k nestandardní epidemiologické situaci, která nám neumožňuje konat Výroční členskou schůzi, která byla vždy posledním termínem zaplacení členských příspěvků, žádám vás o zaplacení členských příspěvků převodem na účet do 31.3.2021.",
        "K zaplacení použijte účet <b class=\"red\">2600505087/2010</b>. Variabilním symbolem je <b class=\"red\">vaše členské číslo</b>, specifický symbol <b class=\"red\">100</b>. Případně použijte zprávu připojenou k platbě, která bude obsahovat slovní popis .",
        "Děkujeme za vaši vstřícnost a těšíme se na setkání v příznivější době."
      ]
    },
    {
      "articleId": 9999999999999,
      "dateOfPublish": "3/16/2021",
      "title": "WDS BRNO",
      "paragraphs": [
        "Vážení vystavovatelé,",
        "s ohledem na momentální situaci a na základě jednání, která probíhají s vedením BVV, jsme nuceni dočasně pozastavit přihlašování na Světovou Výstavu Psů v Brně. Přihlašování bude znovu otevřeno po vyjasnění všech podmínek konání výstavy. Je nám to velice líto, ale bohužel je toto opatření nezbytné. Počet psů, kteří se budou moci výstavy zúčastnit, bude limitován. Limitní počet psů ale bohužel zatím neznáme.",
        "V souvislosti s omezením počtu psů bude pravděpodobně docházet i k dalším změnám (změna rozhodčích, úprava poplatků).",
        "Za komplikace se omlouváme; o nových skutečnostech Vás budeme průběžně informovat.",
        "Lubomír Široký",
        "Předseda ČMKU"
      ],
      "images": [
        "./public/images/2021/2021-wds_logo.jpg"
      ]
    },
    {
      "articleId": 9999999999999,
      "dateOfPublish": "3/16/2021",
      "title": "MVP PRAHA",
      "paragraphs": [
        "Vážení vystavovatelé,",
        "z důvodu přetrvávající nepříznivé pandemické situace a vládních opatření jsme byli nuceni zrušit plánovanou třídenní výstavu Prague Expo Dog 30.7. - 1.8. 2021, a to bez náhradního termínu.,",
        "Pevně doufáme, že se s Vámi a Vašimi čtyřnohými přáteli uvidíme v roce 2022.,",
        "Tým Prague Expo Dog"
      ],
      "images": [
        "./public/images/2021/2021-dog_prague_expo_logo.jpg"
      ]
    },
    {
      "articleId": 9999999999999,
      "dateOfPublish": "3/16/2021",
      "title": "NVP OSTRAVA",
      "paragraphs": [
        "Vážení vystavovatelé,",
        "Přestože jsme udělali maximum pro pořádání výstavy v Ostravě, nastala situace, že v prostorách areálu Výstaviště Černá louka v Ostravě je zřízeno očkovací centrum a nelze zde v plánovaném dubnovém termínu uspořádat Národní výstavu psů.",
        "Bohužel se nám nepodařilo najít pro tuto výstavu vhodný náhradní termín a jsme tudíž nucení pro rok 2021 Národní výstavu psů v Ostravě zrušit.",
        "Lubomír Široký",
        "Předseda ČMKU"
      ],
      "images": [
        "./public/images/2021/2021-cmku_logo.jpg"
      ]
    },
    {
      "articleId": 9999999999999,
      "dateOfPublish": "3/16/2021",
      "title": "NVP BRNO + MVP ŠPILBERKA + MVP DUOCACIB",
      "paragraphs": [
        "Vážení vystavovatelé,",
        "po usilovném jednání o novém termínu Brněnské národní výstavy a mezinárodní výstavy Špilberka máme snad poslední termín.",
        "Nový termín výše uvedených výstav byl stanoven na 14. – 16.5.2021.",
        "14.5.2021 – Brněnská národní výstava psů",
        "15. – 16.5.2021 mezinárodní výstava psů Špilberka",
        "Doufáme, že tento termín už bude termínem definitivním.",
        "Zrušení přihlášek na výše uvedených výstav přijímáme do 31.3.2021.",
        "Kontakt: NVP Brněnská <a href=\"mailto:vystava@vystavabrno.info\">vystava@vystavabrno.info</a>",
        "MVP Špilberka <a href=\"mailto:vystava@cmku.cz\">vystava@cmku.cz</a>",
        "Přeřazení ve třídách, podle věku přihlášených psů, bude provedeno automaticky bez požadavku na doplatek výstavního poplatku.",
        "Uspořádání těchto výstav bude vyžadovat určitá omezení. Omezen bude i počet psů, kteří se budou moci výstav zúčastnit. S ohledem na možnost rušení přihlášek, vyhodnotíme po 31.3.2021 počet registrovaných psů a, pokud to situace dovolí, bude dohlašování psů na tyto výstavy znovu otevřeno. Eventuální znovuotevření přihlašování bude krátkodobé a budeme vás o něm informovat. Sledujte, prosím FB profil a webové stránky výstav.",
        "Zároveň bychom vás chtěli informovat, že i nadále hledáme vhodný náhradní termín pro výstavu DuoCACIB Brno.",
        "Doufáme, že přicházející jaro přinese i pozitivní vývoj situace a umožní nám setkat se co nejdříve v přátelské atmosféře na našich výstavách.",
        "Lubomír Široký",
        "Předseda ČMKU"
      ],
      "images": [
        "./public/images/2021/2021-cmku_logo.jpg"
      ]
    },
    {
      "articleId": 9999999999999,
      "dateOfPublish": "12/13/2020",
      "title": "Ročenka",
      "paragraphs": [
        "Vážení členové,",
        "zahájili jsme práce na ročence za rok 2020. Pokud máte zájem přispět k obsahu ročenky svým článkem, učiňte tak do 15.1.2021. Svůj příspěvek zašlete na emailovou adresu <b><a href=\"mailto:rocenka@mskao.cz?subject=Materialy%20do%20rocenky%202020\">rocenka@mskao.cz</a></b>.",
        "Děkujeme"
      ]
    },
    {
      "articleId": 9999999999999,
      "dateOfPublish": "12/22/2020",
      "title": "PF 2021",
      "paragraphs": [
        "<a href=\"./public/pdf/2020/201220-pf_mskao/pf-mskao.jpg\" target=\"_blank\"><img src=\"./public/pdf/2020/201220-pf_mskao/pf-mskao.jpg\" height=\"280\" width=\"370\"></a>"
      ]
    },
    {
      "articleId": 9999999999999,
      "dateOfPublish": "12/13/2020",
      "title": "Inzerce v ročence MSKAO",
      "paragraphs": [
        "Upozorňujeme na možnost uveřejnění inzerce v připravované Ročence MSKAO 2019. Inzeráty prosím posílejte ve formátu tiskového PDF na adresu <a href=\"mailto:rocenka@mskao.cz?subject=Inzerce%20v%20rocence%202020\">rocenka@mskao.cz</a> do 15.1.2020.",
        "Podmínky jsou následující: <ul> <li>celá strana A4 (chovatelský inzerát člen MSKAO 800 Kč/nečlen 1.600 Kč/komerční inzerát 4.000 Kč) </li> <li>½ strany A4 (člen MSKAO 500 Kč/nečlen 1.000 Kč/komerční inzerát 2.000 Kč)</li> <li>¼ strany A4 (člen MSKAO 300 Kč/nečlen 600 Kč/komerční inzerát 1.000 Kč)</li> </ul>",
        "<b><big>Číslo bankovního účtu: 2600505087 / 2010 (FIO banka)</big></b>"
      ]
    },
    {
      "articleId": 9999999999999,
      "dateOfPublish": "12/12/2020",
      "title": "Nová pravidla pro Evropský pohár britských ohařů",
      "paragraphs": [
        "<ul><li><a href=\"./public/pdf/2020/201212-evropska_pravidla_pro_pohary_britskych_oharu/obeznik_FCI_pravidla_evropsky_pohar.pdf\"target=\"_blank\">oběžník s pravidly pro Evropský pohár (cz, fr, de, es) <img src=\"./public/images/pdf.png\"height=\"20\" width=\"20\"></a></li><li><a href=\"./public/pdf/2020/201212-evropska_pravidla_pro_pohary_britskych_oharu/obeznik_FCI_pravidla_evropsky_pohar-en.pdf\"target=\"_blank\">oběžník s pravidly pro Evropský pohár (en, fr, de, es) <img src=\"./public/images/pdf.png\"height=\"20\" width=\"20\"></a></li></ul>",
        "<ul><li><a href=\"./public/pdf/2020/201212-evropska_pravidla_pro_pohary_britskych_oharu/pravidla_evropsky_pohar.pdf\"target=\"_blank\">pravidla pro Evropský pohár <img src=\"./public/images/pdf.png\" height=\"20\" width=\"20\"></a></li><li><a href=\"./public/pdf/2020/201212-evropska_pravidla_pro_pohary_britskych_oharu/pravidla_evropsky_pohar-en.pdf\"target=\"_blank\">regulations of the European cup <img src=\"./public/images/pdf.png\" height=\"20\" width=\"20\"></a></li><li><a href=\"./public/pdf/2020/201212-evropska_pravidla_pro_pohary_britskych_oharu/pravidla_evropsky_pohar-fr.pdf\"target=\"_blank\">règlement de la coupe d'Europe <img src=\"./public/images/pdf.png\" height=\"20\" width=\"20\"></a></li><li><a href=\"./public/pdf/2020/201212-evropska_pravidla_pro_pohary_britskych_oharu/pravidla_evropsky_pohar-es.pdf\"target=\"_blank\">reglamento de la copa Europa <img src=\"./public/images/pdf.png\" height=\"20\" width=\"20\"></a></li></ul>"
      ]
    },
    {
      "articleId": 9999999999999,
      "dateOfPublish": "10/12/2020",
      "title": "Informace k Memoriálu Aloise Sklenáře-NFT:",
      "paragraphs": [
        "Vážení,",
        "letošní ročník Memoriálu Aloise Sklenáře-NFT se ruší!!!!!!",
        "Děkujeme za pochopení"
      ]
    },
    {
      "articleId": 9999999999999,
      "dateOfPublish": "10/5/2020",
      "title": "Informace k podzimním zkouškám ohařů a zkouškám vloh",
      "paragraphs": [
        "Vážení členové a příznivci lovecké kynologie,",
        "v návaznosti na usnesení vlády č. 957 ze dne 30. září 2020, kterým vláda v souladu s čl. 5 a 6 ústavního zákona č. 110/1998 Sb., o bezpečnosti České republiky, vyhlásila pro území  České republiky z důvodu ohrožení zdraví v souvislosti s prokázáním výskytu koronaviru  /označovaný jako SARS-CoV-2/ na území České republiky nouzový stav, <big class=\"red\" style=\"text-decoration: underline;\"><b>se budou konat podzimní zkoušky ohařů a zkoušky vloh bez přítomnosti veřejnosti a doprovodů!</b></big> Zkoušky proběhnou za splnění všech podmínek pouze za účasti psovodů a rozhodčích, a to pouze za účelem složení těchto zkoušek.",
        "<big class=\"red\"><b>Prosím o respektování vládního nařízení!!!</b></big>",
        "Děkuji za pochopení, Eva Illová – předsedkyně MSKAO"
      ]
    },
    {
      "articleId": 9999999999999,
      "dateOfPublish": "10/5/2020",
      "title": "Memoriál Karla Podhajského",
      "paragraphs": [
        "Vítězem 82. Memoriálu Karla Podhajského se stal pointer <b>Aston z Raklesu</b> vedený <b>Petrem Glozou</b>.",
        "<b>Za MSKAO srdečně gratulujeme k úžasnému výsledku.</b>",
        "<div><a href=\"./public/pdf/2020/201002-memorial_karla_podhajskeho/vysledky.pdf\" target=\"_blank\"><img src=\"./public/pdf/2020/201002-memorial_karla_podhajskeho/vysledky.png\" height=\"250\" width=\"320\"></a></div>"
      ],
      "images": [
        "./public/pdf/2020/201002-memorial_karla_podhajskeho/Petr_Gloza_a_Aston_z_Raklesu.jpg",
        "./public/pdf/2020/201002-memorial_karla_podhajskeho/vysledky.png"
      ]
    },
    {
      "articleId": 9999999999999,
      "dateOfPublish": "9/23/2020",
      "title": "Výsledky klubové výstavy v Náměšti na Hané",
      "paragraphs": [
        "Přinášíme výsledky a fotografie z Klubové výstavy z Náměště.",
        "Nejlepším fenou a celkovým vítězem výstavy se stala fena gordonsetra <b>De La Chapelle Manon Lescaut</b>!!! Tímto gratulujeme zároveň všem oceněným a děkujeme všem za účast.",
        "<a href=\"./public/pdf/2020/200927-names_na_hane/vysledky_01.png\" target=\"_blank\"><img src=\"./public/pdf/2020/200927-names_na_hane/vysledky_01.png\" height=\"150\" width=\"220\"></a><a href=\"./public/pdf/2020/200927-names_na_hane/vysledky_02.png\" target=\"_blank\"><img src=\"./public/pdf/2020/200927-names_na_hane/vysledky_02.png\" height=\"150\" width=\"220\"></a><a href=\"./public/pdf/2020/200927-names_na_hane/vysledky_03.png\" target=\"_blank\"><img src=\"./public/pdf/2020/200927-names_na_hane/vysledky_03.png\" height=\"100\" width=\"220\"></a>",
        "<a href=\"./public/pdf/2020/200927-names_na_hane/01.jpg\" target=\"_blank\"><img src=\"./public/pdf/2020/200927-names_na_hane/01.jpg\" height=\"200\" width=\"300\"></a><a href=\"./public/pdf/2020/200927-names_na_hane/02.jpg\" target=\"_blank\"><img src=\"./public/pdf/2020/200927-names_na_hane/02.jpg\" height=\"200\" width=\"300\"></a><a href=\"./public/pdf/2020/200927-names_na_hane/03.jpg\" target=\"_blank\"><img src=\"./public/pdf/2020/200927-names_na_hane/03.jpg\" height=\"200\" width=\"300\"></a><a href=\"./public/pdf/2020/200927-names_na_hane/04.jpg\" target=\"_blank\"><img src=\"./public/pdf/2020/200927-names_na_hane/04.jpg\" height=\"200\" width=\"300\"></a><a href=\"./public/pdf/2020/200927-names_na_hane/05.jpg\" target=\"_blank\"><img src=\"./public/pdf/2020/200927-names_na_hane/05.jpg\" height=\"200\" width=\"300\"></a>"
      ],
      "images": [
        "./public/pdf/2020/200927-names_na_hane/01.jpg"
      ]
    },
    {
      "articleId": 9999999999999,
      "dateOfPublish": "9/23/2020",
      "title": "Aktuality ke klubové výstavě v Náměšti na Hané",
      "paragraphs": [
        "INFO pro ty z vás, kteří se chystají na klubovku do Náměště !!!!!!",
        "Přikládáme citaci z emailu, který klub obdržel od ředitele výstavy.",
        "<blockquote cite=\"\" style=\"border: 1px solid black; padding: 20px\"><p>Vážené dámy a pánové,</p><p>v souvislosti s Mimořádnými opatřeními vydanými dne 23.9.2020 Ministerstvem zdravotnictví ČR Vám oznamujeme, že se <b>Náměšťská výstava dne 27.9.2020  USKUTEČNÍ  !!</b></p><p>Na akce typu výstav, trhů a veletrhů se vztahuje výjimka a mohou se ve venkovních prostorech konat za účasti 1000 osob ve stejný čas v jednom sektoru. Náš areál je rozdělen na 2 sektory (zámek a louka).</p><p>V celém areálu v průběhu výstavy doporučujeme:</p><ul><li>dodržovat základní hygienická pravidla</li><li>používat rozmístěnou či vlastní desinfekci</li><li>dodržovat rozestupy 2 m</li><li>nosit roušku</li></ul><p>Těším se na viděnou, s pozdravem,</p><p>Jirka Zbořil<br>- ředitel výstavy</p></blockquote>"
      ]
    }
  ]
}
